<?xml version="1.0" encoding="UTF-8" standalone="yes"?>
<addons>
<addon id="plugin.video.cristalazul"
       name="[COLOR aqua]CRISTAL AZUL[/COLOR]"
       version="0.0.7"
       provider-name="PICAPAU, LOURDES, SUPERTOPO, LUISMA">
  <requires>
    <import addon="xbmc.python" version="2.1.0"/>
    <import addon="script.module.beautifulsoup" version="3.2.1"/>
    <import addon="script.module.simple.downloader" version="0.9.4"/>
    <import addon="script.module.beautifulsoup4" />
    <import addon="script.module.requests" />
    <import addon="script.module.httplib2" />
    <import addon="script.module.liveresolver" version="0.1.24" optional="true"/>
    <import addon="script.module.youtube.dl" optional="true"/>
    <import addon="plugin.video.youtube" />
    <import addon="script.module.urlresolver" />
	<import addon="script.module.resolveurl" />
    <import addon="script.module.inputstreamhelper" optional="true"/>
    <import addon="script.module.livestreamer" optional="true"/>
    <import addon="script.module.slproxy" optional="true"/>
	<import addon="script.module.simplejson" />
    <import addon="script.module.livestreamer" optional="true"/>
    <import addon="script.module.pyamf" optional="true"/>
  </requires>
  <extension point="xbmc.python.pluginsource" library="default.py">
    <provides>video</provides>
  </extension>

   <extension point="xbmc.addon.repository" name="Mi repositorio">

        <dir>
            <info>https://raw.githubusercontent.com/picapaujulen/repositorio/master/Repositorio/addons.xml</info>
            <checksum>https://raw.githubusercontent.com/picapaujulen/repositorio/master/Repositorio/addons.xml.md5</checksum>
            <datadir zip="true">https://raw.githubusercontent.com/picapaujulen/repositorio/master/Repositorio/</datadir>
		</dir>

		<dir>
			<info compressed="false">https://raw.githubusercontent.com/Gujal00/smrzips/master/addons.xml</info>
			<checksum>https://raw.githubusercontent.com/Gujal00/smrzips/master/addons.xml.md5</checksum>
			<datadir zip="true">https://raw.githubusercontent.com/Gujal00/smrzips/master/zips/</datadir>
		</dir>

		<dir>
			<info compressed="false">https://raw.githubusercontent.com/jsergio123/zips/master/addons.xml</info>
			<checksum>https://raw.githubusercontent.com/jsergio123/zips/master/addons.xml.md5</checksum>
			<datadir zip="true">https://raw.githubusercontent.com/jsergio123/zips/master/</datadir>
		</dir>
    </extension>


  <extension point="xbmc.addon.metadata">
    <summary>creado por picapau, lourdes, supertopo y luisma</summary>
    <description>ESTE ADDON NO CONTIENE ENLACES PROPIOS,SON RECOPILACIONES DE LA RED, SOLO SE FACILITA EL ACESSO A ESAS WEBS, ESTAS WEBS SON LAS RESPONSABLES DE LOS CONTENIDOS
	</description>ºº
    <platform>all</platform>
	  <assets>
		<icon>icon.gif</icon>
		<fanart>fanart.jpg</fanart>
	  </assets>
  </extension>
</addon>

<addon id="plugin.video.palantir" name="[COLOR gold]Palantir[/COLOR]" version="0.0.78" provider-name="TierraMedia">
  <requires>
    <import addon="xbmc.python" version="2.24.0"/>
    <import addon="script.module.simple.downloader" version="1.9.5"/>
	<import addon="script.module.requests"/>
    <import addon="script.module.resolveurl" optional="true"/>
    <import addon="script.extendedinfo" optional="true"/>
  </requires>
  <extension point="xbmc.python.pluginsource" library="orthanc.py">
    <provides>video</provides>
  </extension>
  <extension point="xbmc.addon.repository" name="Palantir Repo">
        <info>https://raw.githubusercontent.com/Palantiraddon/Repo/master/Palantir/addons.xml</info>
        <checksum>https://raw.githubusercontent.com/Palantiraddon/Repo/master/Palantir/addons.xml.md5</checksum>
        <datadir zip="true">https://raw.githubusercontent.com/Palantiraddon/repo/master/Palantir/</datadir>
  </extension>
  <extension point="xbmc.addon.metadata">
    <summary>TV</summary>
    <news>[COLOR lime][B] versión 0.0.78 [/B][/COLOR]
        - [Interno] Añadida categoría Genéricos en documentales
    </news>
    <description>Visualiza el contenido de la nube, series, películas.</description>
    <disclaimer>[B][COLOR red]Todo el contenido disponible en este Addon esta sacado de servidores gratuitos, disponible en la red para todos los usuarios.[/B][/COLOR]</disclaimer>
    <language></language>
    <platform>all</platform>
    <assets>
        <icon>icon.png</icon>
        <fanart>fanart.gif</fanart>
    </assets>
    <license></license>
    <forum></forum>
    <website></website>
    <email></email>
    <source></source>
  </extension>
</addon>

<addon id="script.video.F4mProxy" name="F4mProxy" version="2.8.8" provider-name="Shani">
    <requires>
        <import addon="xbmc.python" version="2.1.0" />
        <import addon="script.module.requests" />
    </requires>
    <extension point="xbmc.python.module" library="lib" />
    <extension point="xbmc.python.pluginsource" library="addon.py">
        <provides>executable</provides>
    </extension>
    <extension point="xbmc.addon.metadata">
        <platform>all</platform>
        <summary lang="en">Proxy for f4m</summary>
        <description lang="en">Use this addon to play F4m v1 and v2 streams</description>
    </extension>
</addon>

<addon id="script.quasar.burst" name="Quasar [COLOR FFFF6B00]Burst[/COLOR]" version="0.3.1" provider-name="scakemyer">
    <requires>
        <import addon="xbmc.python" version="2.1.0"/>
        <import addon="plugin.video.quasar" optional="false"/>
    </requires>
    <extension point="xbmc.python.script" library="burst.py">
        <provides>executable</provides>
    </extension>
    <extension point="xbmc.addon.metadata">
        <summary lang="en">Quasar torrents provider</summary>
        <description lang="en">Quasar Burst is a lean and mean multi-provider for Quasar.</description>
        <disclaimer lang="en">The author does not host or distribute any of the content displayed by this addon. The author does not have any affiliation with the content providers.
        </disclaimer>
        <license>WTFPL, Version 2, December 2004. See included LICENSE.</license>
        <website>https://burst.surge.sh</website>
        <source>https://bitbucket.org/scakemyer/script.quasar.burst</source>
        <forum>TODO</forum>
        <assets>
            <icon>icon.png</icon>
            <fanart>fanart.jpg</fanart>
        </assets>
    </extension>
</addon>

<addon id="script.luar"
  version="0.3.5"
  name="Luar"
  provider-name="The Dreamers">
  <requires>
    <import addon="xbmc.python" version="2.25.0"/>
    <import addon="script.module.six" version="1.11.0"/>
    <import addon="script.module.requests"/>
  </requires>
  <extension point="xbmc.python.pluginsource" library="default.py">
    <provides>executable</provides>
  </extension>
  <extension point="xbmc.addon.repository" name="Luar Repo">
    <info>http://luar.xyz/repor/addons.xml</info>
    <checksum>http://luar.xyz/repor/addons.xml.md5</checksum>
    <datadir zip="true">http://luar.xyz/repor/</datadir>
  </extension>
  <extension point="xbmc.addon.metadata">
    <platform>all</platform>
    <summary lang="es">Script instalador de complementos para Kodi.</summary>
    <description lang="es">Selecciona, instala y disfruta.</description>
    <disclaimer lang="es"></disclaimer>
    <assets>
      <icon>icon.gif</icon>
      <fanart>fanart.jpg</fanart>
      <screenshot>resources/screenshot000.jpg</screenshot>
      <screenshot>resources/screenshot001.jpg</screenshot>
      <screenshot>resources/screenshot002.jpg</screenshot>
    </assets>
  </extension>
</addon>

<addon id="plugin.video.alfa" name="Alfa" version="3.1.11" provider-name="Alfa Addon">
  <requires>
    <import addon="script.module.requests"/>
    <import addon="script.module.beautifulsoup4" version="4.5.3"/>
    <import addon="script.module.html5lib" version="0.999.0"/>
    <import addon="script.alfa-update-helper" optional="true"/>
  </requires>
  <extension point="xbmc.python.pluginsource" library="default.py">
    <provides>video</provides>
  </extension>
  <extension point="xbmc.addon.metadata">
    <summary lang="es">Navega con Kodi por páginas web.</summary>
    <assets>
      <icon>resources/icono_3.png</icon>
      <fanart>resources/fanart1_2.jpg</fanart>
      <screenshot>resources/media/themes/ss/1.jpg</screenshot>
      <screenshot>resources/media/themes/ss/2.jpg</screenshot>
      <screenshot>resources/media/themes/ss/3.jpg</screenshot>
      <screenshot>resources/media/themes/ss/4.jpg</screenshot>
    </assets>
      <news>[B]Estos son los cambios para esta versión:[/B]

      [COLOR green][B]Arreglos[/B][/COLOR]
      ¤ Areadocumental                        ¤ Estrenosdoramas                         ¤ HDFull
      ¤ PoseidonHD                               ¤ Grantorrent
      ¤ +18

      [COLOR green][B]Novedades[/B][/COLOR]
      ¤ +18

      Agradecimientos a @DamianBacalov por su participación en esta versión
    </news>
    <description lang="es">Navega con Kodi por páginas web para ver sus videos de manera fácil.</description>
    <summary lang="en">Browse web pages using Kodi</summary>
    <description lang="en">Browse web pages using Kodi, you can easily watch their video content.</description>
    <disclaimer>[COLOR red]The owners and submitters to this addon do not host or distribute any of the content displayed by these addons nor do they have any affiliation with the content providers.[/COLOR]</disclaimer>
    <platform>all</platform>
    <license>GNU GPL v3</license>
    <forum>foro</forum>
    <website>web</website>
    <email>my@email.com</email>
    <source>https://github.com/alfa-addon/addon</source>
  </extension>
  <extension point="xbmc.service" library="videolibrary_service.py" start="login|startup">
  </extension>
</addon>

<addon id="plugin.video.1x2"
  version="1.0.27"
  name="1x2"
  provider-name="Team NS">
  <requires>
    <import addon="xbmc.python" version="2.19.0"/>
    <import addon="script.module.requests" version="2.19.1"/>
    <import addon="script.module.routing"/>
    <import addon="inputstream.adaptive" optional="true"/>
    <import addon="plugin.video.youtube"/>
    <import addon="script.video.F4mProxy" version="2.8.8"/>
    <import addon="plugin.video.f4mTester" version="2.7.2"/>
    <import addon="script.module.TvTap"/>
    <import addon="program.plexus"/>
  </requires>
  <extension point="xbmc.python.pluginsource" library="addon.py">
    <provides>video</provides>
  </extension>
  <extension point="xbmc.addon.metadata">
    <platform>all</platform>
    <summary lang="es">Los videos son proporcionados por personas ... en línea ... en algún lugar...</summary>
    <description lang="es">Los videos son proporcionados por personas ... en línea ... en algún lugar...</description>
    <disclaimer lang="es">El autor no almacena ni distribuye ninguno de los contenidos que se muestran en este addon. El autor no tiene ninguna afiliación con el proveedor de contenidos.</disclaimer>
    <assets>
      <icon>icon.gif</icon>
      <fanart>fanart.jpg</fanart>
    </assets>
  </extension>
</addon>

<addon id="script.plexus.patcher" name="Plexus Patcher" version="1.0.7" provider-name="Canna_76">
	<requires>
		<import addon="xbmc.python" version="2.14.0"/>
		<import addon="program.plexus" />
	</requires>
	<extension point="xbmc.python.script" library="addon.py">
		<provides>executable</provides>
	</extension>
	<extension point="xbmc.addon.metadata">
		<platform>all</platform>
		<summary lang="es">Modifica Acestream Plexus Rpi2 3 y Amlogic</summary>
		<description lang="es">Acestream 3.1.48</description>
		<license>GNU General Public License, v2</license>
		<language></language>
		<forum></forum>
		<disclaimer>Agradecimientos al grupo de Telegram Acestream Spanish y a los usuarios Hanni3al, Bit, Crashillo, Lucas, Alberto y un largo etcetera que han hecho posible este parche.
		</disclaimer>
		<source></source>
		<website></website>
		<email></email>
		<assets>
			<icon>icon.png</icon>
			<fanart>fanart.jpg</fanart>
			<screenshot></screenshot>
		</assets>
		<news></news>
	</extension>
</addon>

<addon id="plugin.video.f4mTester" version="2.7.1" name="f4mTester" provider-name="Shani">
    <requires>
        <import addon="xbmc.python" version="2.1.0"/>
        <import addon="script.video.F4mProxy" version="2.7.1"/>
    </requires>
    <extension point="xbmc.python.pluginsource" library="default.py">
        <provides>video</provides>
    </extension>


    <extension point="xbmc.addon.metadata">
        <summary>f4mTester</summary>
        <description></description>
        <platform>all</platform>
    </extension>
</addon>

<addon id="plugin.video.plexus-streams"
       name="Plexus-Streams"
       version="2.0.69b"
       provider-name="D4FC (Mod by Teco)">
  <requires>
    <import addon="xbmc.python" version="2.1.0"/>
    <import addon="script.module.beautifulsoup" version="3.0.8"/>
    <import addon="script.module.pytz" />
    <import addon="script.module.requests" />
    <import addon="script.module.mechanize" version="0.2.6"/>
    <import addon="program.plexus" />
  </requires>
  <extension point="xbmc.python.pluginsource"
            library="default.py">
        <provides>video</provides>
  </extension>
  <extension point="xbmc.addon.metadata">
    <summary>Plexus wrapper</summary>
    <description lang="es">Mod By Teco</description>
    <disclaimer lang="en">The authors does not host nor distribute any of the content you may watch using this addon. The authors have no affiliation with any of the content providers. This addon does not track its users.</disclaimer>
    <platform>all</platform>
  </extension>
</addon>

<addon id="program.plexus"
       name="Plexus"
       version="0.1.8"
       provider-name="tvaddons">
  <requires>
    <import addon="xbmc.python" version="2.1.0"/>
    <import addon="script.module.requests" />
  </requires>
  <extension point="xbmc.python.pluginsource"
            library="default.py">
        <provides>executable</provides>
  </extension>

  <extension point="xbmc.addon.metadata">
    <summary>SopCast and AceStream for Kodi</summary>
    <description lang="en">Plexus - Any complex structure containing an intricate network of parts. Plexus brings native peer-to-peer support (AceStream and SopCast) for Kodi Entertainment Center for several platforms.[CR][CR]Documentation: (missing)</description>
    <description lang="pt">Plexus - Uma estrutura complexa constituída por uma rede de partes. O Plexus adiciona suporte peer-to-peer nativo (AceStream e Sopcast) ao Kodi Entertainment Center para várias plataformas.[CR][CR]Documentação: (em falta)</description>
    <description lang="es">Plexus - Una estructura compleja conteniendo una intrincada red de partes. Plexus añade soporte nativo peer-to-peer (AceStream y SopCast) al Centro de Entretenimiento Kodi para varias plataformas.[CR][CR]Documentacion: (falta)</description>
	<disclaimer lang="en">The author does not host nor distribute any of the content you may watch using this addon. The author has no part in the development of any included technologies. When seeking help in Kodi's forum please respect rules (http://kodi.wiki/view/Forum_rules).</disclaimer>
    <disclaimer lang="pt">Os autores não alojam nem distribuem nenhum do conteúdo que poderá ser reproduzido a partir deste addon. Os autores não têm qualquer parte no desenvolvimento de qualquer uma das tecnologias. Se procurar ajuda no fórum oficial do Kodi por favor respeite as regras do fórum (http://kodi.wiki/view/Forum_rules).</disclaimer>
   	<disclaimer lang="es">El autor no aloja ni distribuye cualquier contenido que ud. pudiera reproducir usando este addon. El autor no tiene participacion en el desarrollo de cualquier tecnologia incluida. Cuando requiera ayuda en el foro de Kodi por favor respete las reglas (http://kodi.wiki/view/Forum_rules).</disclaimer>
    <platform>all</platform>
	<forum>https://www.tvaddons.co/forums</forum>
	<website>https://www.tvaddons.co</website>
  </extension>
</addon>

<addon id="plugin.program.indigo" version="4.0.18" name="Indigo" provider-name="tvaddons">
	<requires>
		<import addon="xbmc.python" version="2.1.0"/>
	</requires>
    <extension point="xbmc.python.pluginsource" library="default.py">
        <provides>video executable</provides>
    </extension>
    <extension point="xbmc.service" library="service.py" start="startup"/>
    <extension point="xbmc.addon.metadata">
        <summary lang="en">Indigo is your gateway to the world of unofficial Kodi addons!</summary>
        <description lang="en">Indigo is your gateway to the world of unofficial Kodi addons! Please visit www.tvaddons.co for support.</description>
        <disclaimer lang="en">Kodi is a registered trademark of the XBMC Foundation. We are not connected to or in any other way affiliated with Kodi, Team Kodi, or the XBMC Foundation. Furthermore, any software, addons, or products offered by us will receive no support in official Kodi channels, including the Kodi forums and various social networks.</disclaimer>
        <language>en</language>
        <platform>all</platform>
        <forum>https://www.tvaddons.co/forums</forum>
        <website>https://www.tvaddons.co</website>
        <source>https://github.com/tvaddonsco/plugin.program.indigo</source>
    </extension>
</addon>

<addon id="repository.balandro" name="Balandro Repo" version="1.0.3" provider-name="Balandro">
	<requires>
		<import addon="xbmc.addon" version="12.0.0"/>
	</requires>

    <extension point="xbmc.addon.repository" name="Balandro Repo">
        <info>https://balandro.tk/repo/addons.xml</info>
        <checksum>https://balandro.tk/repo/addons.xml.md5</checksum>
        <datadir zip="true">https://balandro.tk/repo</datadir>
    </extension>

    <extension point="xbmc.addon.metadata">
        <summary>Repositorio para Balandro</summary>
        <description>Balandro es un navegador para webs con vídeos de películas y series.</description>
        <disclaimer>The owners and submitters to this repository do not host or distribute any of the content displayed by these addons nor do they have any affiliation with the content providers.</disclaimer>
        <platform>all</platform>
    </extension>

</addon>

<addon id="repository.xbmchub" name="TVADDONS.CO Add-on Repository" version="3.0.0" provider-name="tvaddons">
	<extension point="xbmc.addon.repository" name="TVADDONS.CO Add-on Repository">
	<dir>
		<info compressed="false">https://github.com/tvaddonsco/tva-resolvers-repo/raw/master/addons.xml</info>
		<checksum>https://github.com/tvaddonsco/tva-resolvers-repo/raw/master/addons.xml.md5</checksum>
		<datadir zip="true">https://github.com/tvaddonsco/tva-resolvers-repo/raw/master/zips/</datadir>
	</dir>

    <dir>
		<info compressed="false">https://github.com/tvaddonsco/tva-release-repo/raw/master/addons.xml</info>
		<checksum>https://github.com/tvaddonsco/tva-release-repo/raw/master/addons.xml.md5</checksum>
		<datadir zip="true">https://github.com/tvaddonsco/tva-release-repo/raw/master/</datadir>
    </dir>
	</extension>
	<extension point="xbmc.addon.metadata">
		<summary>Unofficial Kodi Addons from TVADDONS.CO</summary>
		<description>Unofficial Kodi Addons from the TVADDONS.CO Add-on Repository. Please visit www.tvaddons.co for support!

Kodi is a registered trademark of the XBMC Foundation. We are not connected to or in any other way affiliated with Kodi, Team Kodi, or the XBMC Foundation.</description>
         <disclaimer>TVADDONS.CO did not make all the add-ons in this repository and is not responsible for their content.</disclaimer>
		<platform>all</platform>
                <forum>https://www.tvaddons.co/forums</forum>
                <website>https://www.tvaddons.co</website>
	</extension>
</addon>

<addon id="plugin.video.tvalacarta" name="[COLOR lime]Tv[/COLOR][COLOR white]ala[/COLOR][COLOR lime]carta[/COLOR]" version="4.2.0" provider-name="tvalacarta">
  <requires>
    <import addon="xbmc.python" version="2.1.0"/>
  </requires>
  <extension point="xbmc.python.pluginsource" library="default.py">
    <provides>video</provides>
  </extension>
  <extension point="xbmc.addon.metadata">
    <summary lang="es">Televisión a la carta</summary>
    <description lang="es">Para ver la televisión por Internet, a la carta y desde tu media center</description>
    <summary lang="en">TV on demand (Spanish)</summary>
    <description lang="en">Watch on demand spanish TV on your media center</description>
    <platform>all</platform>
    <license>GNU GPL v3</license>
    <forum>http://www.mimediacenter.info/foro</forum>
    <website>http://blog.tvalacarta.info/plugin-xbmc/tvalacarta</website>
    <email>tvalacarta@gmail.com</email>
    <source>https://github.com/tvalacarta/tvalacarta</source>
  </extension>
  <extension point="xbmc.service" library="service.py" start="login|startup">
  </extension>
</addon>

<addon id="plugin.video.youtube" name="YouTube" version="6.8.3" provider-name="anxdpanic, bromix">
    <requires>
        <import addon="xbmc.python" version="2.20.0"/>
        <import addon="script.module.six" version="1.11.0"/>
        <import addon="script.module.requests" version="2.12.4"/>
        <import addon="script.module.inputstreamhelper" version="0.2.2" optional="true"/>
    </requires>
    <extension point="xbmc.python.pluginsource" library="resources/lib/default.py">
        <provides>video</provides>
    </extension>
    <extension point="xbmc.service" library="resources/lib/startup.py" start="login"/>
    <extension point="xbmc.python.module" library="resources/lib/"/>
    <extension point="xbmc.addon.metadata">
        <news>
[fix] playback of some videos
[fix] notifications for some languages |contrib: Mutronics|
[fix] fix rating videos causing and error even though it succeeded
[upd] cache javascript player url for 4 hours, reduces http requests per play by 1
[upd] use new settings format on Kodi 19
[lang] el_gr strings |contrib: twilight0|
[lang] hu_hu strings |contrib: thelacesz|
        </news>
        <assets>
            <icon>icon.png</icon>
            <fanart>fanart.jpg</fanart>
        </assets>
        <summary lang="en_GB">Plugin for YouTube</summary>
        <description lang="en_GB">YouTube is one of the biggest video-sharing websites of the world.</description>
        <disclaimer lang="en_GB">This plugin is not endorsed by Google</disclaimer>
        <summary lang="he_IL">תוסף עבור YouTube</summary>
        <description lang="he_IL">YouTube הוא אחד מאתרי שיתוף הווידאו הגדולים בעולם.</description>
        <summary lang="de_DE">Plugin für YouTube</summary>
        <description lang="de_DE">YouTube ist eines der größten Video-Sharing-Websites der Welt.</description>
        <summary lang="pl_PL">Wtyczka YouTube</summary>
        <description lang="pl_PL">YouTube jest jednym z największych na świecie serwisów udostępniania wideo.</description>
        <summary lang="hu_HU">YouTube kiegészítő</summary>
        <description lang="hu_HU">A YouTube világ egyik legnagyobb videómegosztó weboldala.</description>
        <summary lang="es_ES">Plugin para YouTube</summary>
        <description lang="es_ES">YouTube es uno de los sitios web más grande del mundo para compartir vídeos.</description>
        <disclaimer lang="es_ES">Este add-on no está respaldado por Google</disclaimer>
        <summary lang="es_MX">Plugin para YouTube</summary>
        <description lang="es_MX">YouTube es uno de los más grandes sitios web de intercambio de videos del mundo.</description>
        <disclaimer lang="es_MX">Este add-on no está respaldado por Google</disclaimer>
        <summary lang="ru_RU">Видеодополнение YouTube</summary>
        <description lang="ru_RU">YouTube - популярнейший видеохостинговый сайт, предоставляющий пользователям услуги хранения, доставки и показа видео.</description>
        <summary lang="fr_FR">Plugin pour YouTube</summary>
        <description lang="fr_FR">YouTube est l'un des plus grands sites de partage vidéos du monde.</description>
        <summary lang="zh_CN">YouTube附加元件</summary>
        <description lang="zh_CN">「Youtube」是全世界最大的影片分享網站</description>
        <summary lang="zh_TW">YouTube附加元件</summary>
        <description lang="zh_TW">「Youtube」是全世界最大的影片分享網站</description>
        <disclaimer lang="zh_TW">此附加元件未由Google支持</disclaimer>
        <summary lang="bg_BG">Добавка за YouTube</summary>
        <description lang="bg_BG">YouTube е един от най-големите уеб сайтове за споделяне на видео в целия свят.</description>
        <summary lang="el_GR">Πρόσθετο YouTube</summary>
        <description lang="el_GR">Το YouTube είναι μία από τις μεγαλύτερες ιστοσελίδες διαμοιρασμού βίντεο στον κόσμο.</description>
        <disclaimer lang="el_GR">Η παρούσα μικροεφαρμογή δεν έχει υϊοθετηθεί από την Google</disclaimer>
        <summary lang="nb_NO">Tillegg for YouTube</summary>
        <description lang="nb_NO">YouTube er en av verdens største nettsider for videodeling.</description>
        <summary lang="ko_KR">유튜브 플러그인</summary>
        <description lang="ko_KR">유튜브는 세상에서 가장 큰 동영상 공유 사이트 중의 하나입니다.</description>
        <summary lang="cs_CZ">Plugin pro YouTube</summary>
        <description lang="cs_CZ">YouTube je jedna z největších webových stránek světa sdílející video.</description>
        <disclaimer lang="cs_CZ">Tento plugin není schválen společností Google</disclaimer>
        <summary lang="tr_TR">YouTube için eklenti</summary>
        <description lang="tr_TR">YouTube, dünya üzerindeki en büyük video paylaşma platformlarından birisidir</description>
        <disclaimer lang="tr_TR">Bu eklenti Google tarafından üretilmemiştir</disclaimer>
        <platform>all</platform>
        <license>GPL-2.0-only</license>
        <forum>https://ytaddon.page.link/forum</forum>
        <website>https://www.youtube.com</website>
        <email>ytplugin at datanet dot ws</email>
        <source>https://github.com/jdf76/plugin.video.youtube</source>
        <reuselanguageinvoker>true</reuselanguageinvoker>
    </extension>
</addon>
<!-- unofficial -->
</addons>
